ciscompphwdiscovery/__init__.py
ciscompphwdiscovery/__main__.py
ciscompphwdiscovery/app.py
ciscompphwdiscovery/schema/10.0/AXLAPI.wsdl
ciscompphwdiscovery/schema/10.0/AXLEnums.xsd
ciscompphwdiscovery/schema/10.0/AXLSoap.xsd
ciscompphwdiscovery/schema/10.5/AXLAPI.wsdl
ciscompphwdiscovery/schema/10.5/AXLEnums.xsd
ciscompphwdiscovery/schema/10.5/AXLSoap.xsd
ciscompphwdiscovery/schema/11.0/AXLAPI.wsdl
ciscompphwdiscovery/schema/11.0/AXLEnums.xsd
ciscompphwdiscovery/schema/11.0/AXLSoap.xsd
ciscompphwdiscovery/schema/11.5/AXLAPI.wsdl
ciscompphwdiscovery/schema/11.5/AXLEnums.xsd
ciscompphwdiscovery/schema/11.5/AXLSoap.xsd
ciscompphwdiscovery/schema/12.0/AXLAPI.wsdl
ciscompphwdiscovery/schema/12.0/AXLEnums.xsd
ciscompphwdiscovery/schema/12.0/AXLSoap.xsd
ciscompphwdiscovery/schema/12.5/AXLAPI.wsdl
ciscompphwdiscovery/schema/12.5/AXLEnums.xsd
ciscompphwdiscovery/schema/12.5/AXLSoap.xsd
ciscompphwdiscovery/schema/14.0/AXLAPI.wsdl
ciscompphwdiscovery/schema/14.0/AXLEnums.xsd
ciscompphwdiscovery/schema/14.0/AXLSoap.xsd
ciscompphwdiscovery-1.3.29.dist-info/entry_points.txt
ciscompphwdiscovery-1.3.29.dist-info/WHEEL
ciscompphwdiscovery-1.3.29.dist-info/METADATA
ciscompphwdiscovery-1.3.29.dist-info/licenses/LICENSE
ciscompphwdiscovery-1.3.29.dist-info/RECORD
