Metadata-Version: 2.1
Name: ciscompphwdiscovery
Version: 1.3.29
Summary: Cisco MPP Migration Hardware Revision Discovery
License: MIT
Keywords: Cisco,MPP,CUCM,AXL,7821,7841,7861
Author-email: Collin Moerman <collin@moerman.us>
Requires-Python: >=3.7
Classifier: License :: OSI Approved :: MIT License
Classifier: Natural Language :: English
Classifier: Operating System :: OS Independent
Classifier: Programming Language :: Python :: 3
Classifier: Topic :: Communications
Classifier: Topic :: System :: Networking
Requires-Dist: lxml~=4.8.0
Requires-Dist: requests~=2.25.1
Requires-Dist: tqdm~=4.65.0
Requires-Dist: urllib3~=1.26.5
Requires-Dist: zeep~=4.2.1
Project-URL: Homepage, https://github.com/collinmoerman/ciscompphwdiscovery
